cloudprojects/__init__.py
cloudprojects/urls.py
django_cloudprojects-0.3.0.dist-info/LICENSE
django_cloudprojects-0.3.0.dist-info/METADATA
django_cloudprojects-0.3.0.dist-info/WHEEL
django_cloudprojects-0.3.0.dist-info/top_level.txt
django_cloudprojects-0.3.0.dist-info/RECORD
