Metadata-Version: 2.1
Name: django-cloudprojects
Version: 0.3.0
Summary: Self-service onboarding and management platform for your cloud projects.
Home-page: https://github.com/painless-software/django-cloudprojects
Author: Peter Bittner
Author-email: django@bittner.it
License: UNKNOWN
Keywords: cloud,kubernetes,openshift,django,software,development,hosting
Platform: UNKNOWN
Classifier: Development Status :: 3 - Alpha
Classifier: Intended Audience :: Developers
Classifier: Intended Audience :: System Administrators
Classifier: License :: OSI Approved :: Apache Software License
Classifier: Framework :: Django
Classifier: Framework :: Django :: 2.2
Classifier: Framework :: Django :: 3.2
Classifier: Framework :: Django :: 4.0
Classifier: Programming Language :: Python
Classifier: Programming Language :: Python :: 3.6
Classifier: Programming Language :: Python :: 3.7
Classifier: Programming Language :: Python :: 3.8
Classifier: Programming Language :: Python :: 3.9
Classifier: Programming Language :: Python :: 3.10
Requires-Python: >=3.6
License-File: LICENSE
Requires-Dist: django-allauth
Provides-Extra: saml
Requires-Dist: python3-saml-django ; extra == 'saml'
